setup.py
Products/__init__.py
Products.QueueCatalog.egg-info/PKG-INFO
Products.QueueCatalog.egg-info/SOURCES.txt
Products.QueueCatalog.egg-info/dependency_links.txt
Products.QueueCatalog.egg-info/namespace_packages.txt
Products.QueueCatalog.egg-info/not-zip-safe
Products.QueueCatalog.egg-info/requires.txt
Products.QueueCatalog.egg-info/top_level.txt
Products/QueueCatalog/CHANGES.txt
Products/QueueCatalog/CatalogEventQueue.py
Products/QueueCatalog/CatalogEventQueueSet.py
Products/QueueCatalog/DEPENDENCIES.txt
Products/QueueCatalog/Processor.py
Products/QueueCatalog/QueueCatalog.py
Products/QueueCatalog/README.txt
Products/QueueCatalog/__init__.py
Products/QueueCatalog/version.txt
Products/QueueCatalog/dtml/add.dtml
Products/QueueCatalog/dtml/queue.dtml
Products/QueueCatalog/help/QueueCatalog-Add.stx
Products/QueueCatalog/help/QueueCatalog-Configure.stx
Products/QueueCatalog/help/QueueCatalog-Queue.stx
Products/QueueCatalog/tests/__init__.py
Products/QueueCatalog/tests/test_CatalogEventQueue.py
Products/QueueCatalog/tests/test_CatalogEventQueueSet.py
Products/QueueCatalog/tests/test_QueueCatalog.py
Products/QueueCatalog/www/QueueCatalog.gif
Products/QueueCatalog/www/edit.zpt