Metadata-Version: 1.0
Name: Products.QueueCatalog
Version: 1.6.0
Summary: QueueCatalog - asynchronous cataloging
Home-page: http://www.zope.org/Members/ctheune/QueueCatalog
Author: Christian Theune
Author-email: ct@gocept.com
License: ZPL (see LICENSE.txt)
Keywords: Zope2 Indexing Catalog Queue
Platform: UNKNOWN
Classifier: Programming Language :: Python
Classifier: Framework :: Zope2
